okeanTweak/__init__.py
okeanTweak/main.py
okeantweak-0.1.2.dist-info/licenses/LICENSE
okeantweak-0.1.2.dist-info/METADATA
okeantweak-0.1.2.dist-info/WHEEL
okeantweak-0.1.2.dist-info/entry_points.txt
okeantweak-0.1.2.dist-info/top_level.txt
okeantweak-0.1.2.dist-info/RECORD
